{"nodes": [{"id": "f_svg_website_services_ffmpeg_js", "label": "ffmpeg.js", "file_type": "code", "source_file": "F:\\svg website\\services\\ffmpeg.js", "source_location": "L1"}, {"id": "services_ffmpeg_runffmpeg", "label": "runFFmpeg()", "file_type": "code", "source_file": "F:\\svg website\\services\\ffmpeg.js", "source_location": "L17"}, {"id": "services_ffmpeg_checkffmpeg", "label": "checkFFmpeg()", "file_type": "code", "source_file": "F:\\svg website\\services\\ffmpeg.js", "source_location": "L44"}, {"id": "services_ffmpeg_extractframes", "label": "extractFrames()", "file_type": "code", "source_file": "F:\\svg website\\services\\ffmpeg.js", "source_location": "L60"}, {"id": "services_ffmpeg_removebackground", "label": "removeBackground()", "file_type": "code", "source_file": "F:\\svg website\\services\\ffmpeg.js", "source_location": "L93"}, {"id": "services_ffmpeg_removebackgroundbatch", "label": "removeBackgroundBatch()", "file_type": "code", "source_file": "F:\\svg website\\services\\ffmpeg.js", "source_location": "L131"}, {"id": "services_ffmpeg_framestowebp", "label": "framesToWebP()", "file_type": "code", "source_file": "F:\\svg website\\services\\ffmpeg.js", "source_location": "L151"}, {"id": "services_ffmpeg_framestowebpsequence", "label": "framesToWebPSequence()", "file_type": "code", "source_file": "F:\\svg website\\services\\ffmpeg.js", "source_location": "L182"}, {"id": "services_ffmpeg_framestogif", "label": "framesToGIF()", "file_type": "code", "source_file": "F:\\svg website\\services\\ffmpeg.js", "source_location": "L213"}, {"id": "services_ffmpeg_getvideoinfo", "label": "getVideoInfo()", "file_type": "code", "source_file": "F:\\svg website\\services\\ffmpeg.js", "source_location": "L249"}, {"id": "services_ffmpeg_createtempdir", "label": "createTempDir()", "file_type": "code", "source_file": "F:\\svg website\\services\\ffmpeg.js", "source_location": "L292"}, {"id": "services_ffmpeg_cleanuptempdir", "label": "cleanupTempDir()", "file_type": "code", "source_file": "F:\\svg website\\services\\ffmpeg.js", "source_location": "L302"}], "edges": [{"source": "f_svg_website_services_ffmpeg_js", "target": "services_ffmpeg_runffmpeg", "relation": "contains", "confidence": "EXTRACTED", "source_file": "F:\\svg website\\services\\ffmpeg.js", "source_location": "L17", "weight": 1.0}, {"source": "f_svg_website_services_ffmpeg_js", "target": "services_ffmpeg_checkffmpeg", "relation": "contains", "confidence": "EXTRACTED", "source_file": "F:\\svg website\\services\\ffmpeg.js", "source_location": "L44", "weight": 1.0}, {"source": "f_svg_website_services_ffmpeg_js", "target": "services_ffmpeg_extractframes", "relation": "contains", "confidence": "EXTRACTED", "source_file": "F:\\svg website\\services\\ffmpeg.js", "source_location": "L60", "weight": 1.0}, {"source": "f_svg_website_services_ffmpeg_js", "target": "services_ffmpeg_removebackground", "relation": "contains", "confidence": "EXTRACTED", "source_file": "F:\\svg website\\services\\ffmpeg.js", "source_location": "L93", "weight": 1.0}, {"source": "f_svg_website_services_ffmpeg_js", "target": "services_ffmpeg_removebackgroundbatch", "relation": "contains", "confidence": "EXTRACTED", "source_file": "F:\\svg website\\services\\ffmpeg.js", "source_location": "L131", "weight": 1.0}, {"source": "f_svg_website_services_ffmpeg_js", "target": "services_ffmpeg_framestowebp", "relation": "contains", "confidence": "EXTRACTED", "source_file": "F:\\svg website\\services\\ffmpeg.js", "source_location": "L151", "weight": 1.0}, {"source": "f_svg_website_services_ffmpeg_js", "target": "services_ffmpeg_framestowebpsequence", "relation": "contains", "confidence": "EXTRACTED", "source_file": "F:\\svg website\\services\\ffmpeg.js", "source_location": "L182", "weight": 1.0}, {"source": "f_svg_website_services_ffmpeg_js", "target": "services_ffmpeg_framestogif", "relation": "contains", "confidence": "EXTRACTED", "source_file": "F:\\svg website\\services\\ffmpeg.js", "source_location": "L213", "weight": 1.0}, {"source": "f_svg_website_services_ffmpeg_js", "target": "services_ffmpeg_getvideoinfo", "relation": "contains", "confidence": "EXTRACTED", "source_file": "F:\\svg website\\services\\ffmpeg.js", "source_location": "L249", "weight": 1.0}, {"source": "f_svg_website_services_ffmpeg_js", "target": "services_ffmpeg_createtempdir", "relation": "contains", "confidence": "EXTRACTED", "source_file": "F:\\svg website\\services\\ffmpeg.js", "source_location": "L292", "weight": 1.0}, {"source": "f_svg_website_services_ffmpeg_js", "target": "services_ffmpeg_cleanuptempdir", "relation": "contains", "confidence": "EXTRACTED", "source_file": "F:\\svg website\\services\\ffmpeg.js", "source_location": "L302", "weight": 1.0}, {"source": "services_ffmpeg_checkffmpeg", "target": "services_ffmpeg_runffmpeg", "relation": "calls", "context": "call", "confidence": "EXTRACTED", "source_file": "F:\\svg website\\services\\ffmpeg.js", "source_location": "L46", "weight": 1.0}, {"source": "services_ffmpeg_extractframes", "target": "services_ffmpeg_runffmpeg", "relation": "calls", "context": "call", "confidence": "EXTRACTED", "source_file": "F:\\svg website\\services\\ffmpeg.js", "source_location": "L76", "weight": 1.0}, {"source": "services_ffmpeg_removebackground", "target": "services_ffmpeg_runffmpeg", "relation": "calls", "context": "call", "confidence": "EXTRACTED", "source_file": "F:\\svg website\\services\\ffmpeg.js", "source_location": "L121", "weight": 1.0}, {"source": "services_ffmpeg_removebackgroundbatch", "target": "services_ffmpeg_removebackground", "relation": "calls", "context": "call", "confidence": "EXTRACTED", "source_file": "F:\\svg website\\services\\ffmpeg.js", "source_location": "L138", "weight": 1.0}, {"source": "services_ffmpeg_framestowebp", "target": "services_ffmpeg_runffmpeg", "relation": "calls", "context": "call", "confidence": "EXTRACTED", "source_file": "F:\\svg website\\services\\ffmpeg.js", "source_location": "L172", "weight": 1.0}, {"source": "services_ffmpeg_framestowebpsequence", "target": "services_ffmpeg_runffmpeg", "relation": "calls", "context": "call", "confidence": "EXTRACTED", "source_file": "F:\\svg website\\services\\ffmpeg.js", "source_location": "L203", "weight": 1.0}, {"source": "services_ffmpeg_framestogif", "target": "services_ffmpeg_runffmpeg", "relation": "calls", "context": "call", "confidence": "EXTRACTED", "source_file": "F:\\svg website\\services\\ffmpeg.js", "source_location": "L221", "weight": 1.0}], "raw_calls": [{"caller_nid": "services_ffmpeg_extractframes", "callee": "mkdirSync", "is_member_call": true, "source_file": "F:\\svg website\\services\\ffmpeg.js", "source_location": "L64"}, {"caller_nid": "services_ffmpeg_extractframes", "callee": "join", "is_member_call": true, "source_file": "F:\\svg website\\services\\ffmpeg.js", "source_location": "L66"}, {"caller_nid": "services_ffmpeg_extractframes", "callee": "map", "is_member_call": true, "source_file": "F:\\svg website\\services\\ffmpeg.js", "source_location": "L79"}, {"caller_nid": "services_ffmpeg_extractframes", "callee": "sort", "is_member_call": true, "source_file": "F:\\svg website\\services\\ffmpeg.js", "source_location": "L79"}, {"caller_nid": "services_ffmpeg_extractframes", "callee": "filter", "is_member_call": true, "source_file": "F:\\svg website\\services\\ffmpeg.js", "source_location": "L79"}, {"caller_nid": "services_ffmpeg_extractframes", "callee": "readdirSync", "is_member_call": true, "source_file": "F:\\svg website\\services\\ffmpeg.js", "source_location": "L79"}, {"caller_nid": "services_ffmpeg_removebackground", "callee": "toLowerCase", "is_member_call": true, "source_file": "F:\\svg website\\services\\ffmpeg.js", "source_location": "L100"}, {"caller_nid": "services_ffmpeg_removebackgroundbatch", "callee": "mkdirSync", "is_member_call": true, "source_file": "F:\\svg website\\services\\ffmpeg.js", "source_location": "L132"}, {"caller_nid": "services_ffmpeg_removebackgroundbatch", "callee": "join", "is_member_call": true, "source_file": "F:\\svg website\\services\\ffmpeg.js", "source_location": "L137"}, {"caller_nid": "services_ffmpeg_removebackgroundbatch", "callee": "padStart", "is_member_call": true, "source_file": "F:\\svg website\\services\\ffmpeg.js", "source_location": "L137"}, {"caller_nid": "services_ffmpeg_removebackgroundbatch", "callee": "String", "is_member_call": false, "source_file": "F:\\svg website\\services\\ffmpeg.js", "source_location": "L137"}, {"caller_nid": "services_ffmpeg_removebackgroundbatch", "callee": "push", "is_member_call": true, "source_file": "F:\\svg website\\services\\ffmpeg.js", "source_location": "L139"}, {"caller_nid": "services_ffmpeg_framestowebp", "callee": "join", "is_member_call": true, "source_file": "F:\\svg website\\services\\ffmpeg.js", "source_location": "L156"}, {"caller_nid": "services_ffmpeg_framestowebp", "callee": "String", "is_member_call": false, "source_file": "F:\\svg website\\services\\ffmpeg.js", "source_location": "L160"}, {"caller_nid": "services_ffmpeg_framestowebp", "callee": "String", "is_member_call": false, "source_file": "F:\\svg website\\services\\ffmpeg.js", "source_location": "L166"}, {"caller_nid": "services_ffmpeg_framestowebp", "callee": "String", "is_member_call": false, "source_file": "F:\\svg website\\services\\ffmpeg.js", "source_location": "L167"}, {"caller_nid": "services_ffmpeg_framestowebpsequence", "callee": "join", "is_member_call": true, "source_file": "F:\\svg website\\services\\ffmpeg.js", "source_location": "L187"}, {"caller_nid": "services_ffmpeg_framestowebpsequence", "callee": "String", "is_member_call": false, "source_file": "F:\\svg website\\services\\ffmpeg.js", "source_location": "L191"}, {"caller_nid": "services_ffmpeg_framestowebpsequence", "callee": "String", "is_member_call": false, "source_file": "F:\\svg website\\services\\ffmpeg.js", "source_location": "L196"}, {"caller_nid": "services_ffmpeg_framestowebpsequence", "callee": "String", "is_member_call": false, "source_file": "F:\\svg website\\services\\ffmpeg.js", "source_location": "L197"}, {"caller_nid": "services_ffmpeg_framestogif", "callee": "join", "is_member_call": true, "source_file": "F:\\svg website\\services\\ffmpeg.js", "source_location": "L217"}, {"caller_nid": "services_ffmpeg_framestogif", "callee": "join", "is_member_call": true, "source_file": "F:\\svg website\\services\\ffmpeg.js", "source_location": "L218"}, {"caller_nid": "services_ffmpeg_framestogif", "callee": "String", "is_member_call": false, "source_file": "F:\\svg website\\services\\ffmpeg.js", "source_location": "L223"}, {"caller_nid": "services_ffmpeg_framestogif", "callee": "String", "is_member_call": false, "source_file": "F:\\svg website\\services\\ffmpeg.js", "source_location": "L232"}, {"caller_nid": "services_ffmpeg_framestogif", "callee": "unlinkSync", "is_member_call": true, "source_file": "F:\\svg website\\services\\ffmpeg.js", "source_location": "L241"}, {"caller_nid": "services_ffmpeg_createtempdir", "callee": "join", "is_member_call": true, "source_file": "F:\\svg website\\services\\ffmpeg.js", "source_location": "L293"}, {"caller_nid": "services_ffmpeg_createtempdir", "callee": "tmpdir", "is_member_call": true, "source_file": "F:\\svg website\\services\\ffmpeg.js", "source_location": "L293"}, {"caller_nid": "services_ffmpeg_createtempdir", "callee": "mkdirSync", "is_member_call": true, "source_file": "F:\\svg website\\services\\ffmpeg.js", "source_location": "L294"}, {"caller_nid": "services_ffmpeg_cleanuptempdir", "callee": "rmSync", "is_member_call": true, "source_file": "F:\\svg website\\services\\ffmpeg.js", "source_location": "L304"}, {"caller_nid": "services_ffmpeg_cleanuptempdir", "callee": "error", "is_member_call": true, "source_file": "F:\\svg website\\services\\ffmpeg.js", "source_location": "L306"}]}